<root xmlns:owl="http://www.w3.org/2002/07/owl#" xmlns:pmx="http://www.politicalmashup.nl/extra" xmlns:dc="http://purl.org/dc/elements/1.1/" xmlns:pmd="http://www.politicalmashup.nl/docinfo" xmlns:openpx="https://openparliament.ca/extra" xmlns:dcterms="http://purl.org/dc/terms/" xmlns:html="http://www.w3.org/1999/xhtml" xmlns:rdf="http://www.w3.org/1999/02/22-rdf-syntax-ns#" xmlns:xsd="http://www.w3.org/2001/XMLSchema-datatypes" xmlns:xsi="http://www.w3.org/2001/XMLSchema-instance" xmlns:pm="http://www.politicalmashup.nl">
  <pmd:docinfo>
    <pm:comment>Data is valid with respect to the Relax NG schema http://schema.politicalmashup.nl/memberX.html. This is the open version of http://schema.politicalmashup.nl/member.html</pm:comment>
  </pmd:docinfo>
  <meta pm:id="ca.m.187">
    <dc:identifier>ca.m.187</dc:identifier>
    <dc:format>text/xml</dc:format>
    <dc:type>Members</dc:type>
    <dc:contributor>http://www.politicalmashup.nl</dc:contributor>
    <dc:coverage>
      <country dcterms:ISO3166-1="CA">Canada</country>
    </dc:coverage>
    <dc:creator>http://dilipad.history.ac.uk</dc:creator>
    <dc:language>
      <pm:language dcterms:ISO639-2="eng">English</pm:language>
    </dc:language>
    <dc:publisher>http://www.parl.gc.ca/parlinfo/</dc:publisher>
    <dc:rights>http://www.parl.gc.ca/parlinfo/</dc:rights>
    <dc:date>2015-01-14+01:00</dc:date>
    <dc:title>MARTIN, The Right Hon. Paul Edgar Philippe, P.C., C.C., Hon. B.A., LL.B.</dc:title>
    <dc:description>Member information for: MARTIN, The Right Hon. Paul Edgar Philippe, P.C., C.C., Hon. B.A., LL.B.</dc:description>
    <dc:source>
      <dc:source pm:used-source="true">
        <pm:link pm:linktype="trusted" pm:source="http://www.parl.gc.ca/parlinfo">http://www.parl.gc.ca/parlinfo</pm:link>
      </dc:source>
      <dc:source pm:used-source="true">
        <pm:link pm:linktype="trusted" pm:source="http://www.parl.gc.ca/parlinfo/Files/Parliamentarian.aspx?Item=26693a66-0030-4b80-bea6-f9b33e39e158&amp;Language=E&amp;Section=ALL">http://www.parl.gc.ca/parlinfo/Files/Parliamentarian.aspx?Item=26693a66-0030-4b80-bea6-f9b33e39e158&amp;Language=E&amp;Section=ALL</pm:link>
      </dc:source>
    </dc:source>
    <dc:subject/>
    <dc:relation>All pm:party-ref attributes appearing in http://www.politicalmashup.nl documents refer to http://resolver.politicalmashup.nl/[pm:party-ref] .</dc:relation>
  </meta>
  <pm:member pm:id="ca.m.187">
    <pm:name>
      <pm:full>MARTIN, The Right Hon. Paul Edgar Philippe, P.C., C.C., Hon. B.A., LL.B.</pm:full>
      <pm:first>Paul Edgar Philippe</pm:first>
      <pm:last>Martin</pm:last>
      <pm:titles>
        <pm:title pm:position="prefix" pm:honorific="honorary">The Right Hon.</pm:title>
        <pm:title pm:position="suffix" pm:honorific="academic">P.C.</pm:title>
        <pm:title pm:position="suffix" pm:honorific="academic">C.C.</pm:title>
        <pm:title pm:position="suffix" pm:honorific="academic">Hon. B.A.</pm:title>
        <pm:title pm:position="suffix" pm:honorific="academic">LL.B.</pm:title>
      </pm:titles>
    </pm:name>
    <pm:personal>
      <pm:born pm:date="1938-08-28" pm:granularity="8" pm:place="Windsor, Ontario, Canada"/>
      <pm:gender>male</pm:gender>
    </pm:personal>
    <pm:curriculum>
      <pm:extra-curricular pm:source="http://www.parl.gc.ca/parlinfo/">
        <pm:name>Businessman, lawyer</pm:name>
      </pm:extra-curricular>
    </pm:curriculum>
    <pm:links>
      <pm:link pm:linktype="trusted" pm:source="http://www.parl.gc.ca/parlinfo" pm:description="Parlinfo">http://www.parl.gc.ca/parlinfo/Files/Parliamentarian.aspx?Item=26693a66-0030-4b80-bea6-f9b33e39e158&amp;Language=E&amp;Section=ALL</pm:link>
      <pm:link pm:linktype="photo" pm:source="http://www.parl.gc.ca/parlinfo" pm:description="Portrait photo Parlinfo">http://www.parl.gc.ca/parlinfo/images/Picture.aspx?Item=b285e67f-a19a-4c88-a6b1-ab172ff5abd8</pm:link>
      <pm:link pm:linktype="trusted" pm:source="http://www.parl.gc.ca/parlinfo" pm:description="Personal Website">http://www.paulmartin.ca/</pm:link>
      <pm:link pm:linktype="trusted" pm:source="http://www.parl.gc.ca/parlinfo" pm:description="Order of Canada">http://www.gg.ca/honour.aspx?id=11976&amp;t=12&amp;ln=martin&amp;lan=eng</pm:link>
      <pm:link pm:linktype="dbpedia" pm:source="http://dbpedia.org" pm:description="Dbpedia ()">http://dbpedia.org/resource/Paul_Martin</pm:link>
      <pm:link pm:linktype="wikipedia" pm:source="http://en.wikipedia.org" pm:description="Wikipedia (EN)">http://en.wikipedia.org/wiki/Paul_Martin</pm:link>
      <pm:link pm:linktype="wikipedia" pm:source="http://eo.wikipedia.org/wiki" pm:description="Wikipedia (EO)">http://eo.wikipedia.org/wiki/Paul_Martin</pm:link>
      <pm:link pm:linktype="wikipedia" pm:source="http://zh.wikipedia.org/wiki" pm:description="Wikipedia (ZH)">http://zh.wikipedia.org/wiki/保罗·马丁</pm:link>
      <pm:link pm:linktype="wikipedia" pm:source="http://io.wikipedia.org/wiki" pm:description="Wikipedia (IO)">http://io.wikipedia.org/wiki/Paul_Martin</pm:link>
      <pm:link pm:linktype="wikipedia" pm:source="http://simple.wikipedia.org/wiki" pm:description="Wikipedia (SIMPLE)">http://simple.wikipedia.org/wiki/Paul_Martin_Jr.</pm:link>
      <pm:link pm:linktype="wikipedia" pm:source="http://oc.wikipedia.org/wiki" pm:description="Wikipedia (OC)">http://oc.wikipedia.org/wiki/Paul_Edgar_Philippe_Martin</pm:link>
      <pm:link pm:linktype="wikipedia" pm:source="http://ca.wikipedia.org/wiki" pm:description="Wikipedia (CA)">http://ca.wikipedia.org/wiki/Paul_Martin</pm:link>
      <pm:link pm:linktype="wikipedia" pm:source="http://it.wikipedia.org/wiki" pm:description="Wikipedia (IT)">http://it.wikipedia.org/wiki/Paul_Edgar_Philippe_Martin</pm:link>
      <pm:link pm:linktype="wikipedia" pm:source="http://cy.wikipedia.org/wiki" pm:description="Wikipedia (CY)">http://cy.wikipedia.org/wiki/Paul_Martin</pm:link>
      <pm:link pm:linktype="wikipedia" pm:source="http://gd.wikipedia.org/wiki" pm:description="Wikipedia (GD)">http://gd.wikipedia.org/wiki/Paul_Martin</pm:link>
      <pm:link pm:linktype="wikipedia" pm:source="http://ga.wikipedia.org/wiki" pm:description="Wikipedia (GA)">http://ga.wikipedia.org/wiki/Paul_Martin</pm:link>
      <pm:link pm:linktype="wikipedia" pm:source="http://cs.wikipedia.org/wiki" pm:description="Wikipedia (CS)">http://cs.wikipedia.org/wiki/Paul_Martin_(politik)</pm:link>
      <pm:link pm:linktype="wikipedia" pm:source="http://gl.wikipedia.org/wiki" pm:description="Wikipedia (GL)">http://gl.wikipedia.org/wiki/Paul_Martin</pm:link>
      <pm:link pm:linktype="wikipedia" pm:source="http://id.wikipedia.org/wiki" pm:description="Wikipedia (ID)">http://id.wikipedia.org/wiki/Paul_Martin</pm:link>
      <pm:link pm:linktype="wikipedia" pm:source="http://es.wikipedia.org/wiki" pm:description="Wikipedia (ES)">http://es.wikipedia.org/wiki/Paul_Martin_(político)</pm:link>
      <pm:link pm:linktype="wikipedia" pm:source="http://ru.wikipedia.org/wiki" pm:description="Wikipedia (RU)">http://ru.wikipedia.org/wiki/Мартин,_Пол_Эдгар_Филип</pm:link>
      <pm:link pm:linktype="wikipedia" pm:source="http://nl.wikipedia.org/wiki" pm:description="Wikipedia (NL)">http://nl.wikipedia.org/wiki/Paul_Martin</pm:link>
      <pm:link pm:linktype="wikipedia" pm:source="http://nn.wikipedia.org/wiki" pm:description="Wikipedia (NN)">http://nn.wikipedia.org/wiki/Paul_Martin</pm:link>
      <pm:link pm:linktype="wikipedia" pm:source="http://no.wikipedia.org/wiki" pm:description="Wikipedia (NO)">http://no.wikipedia.org/wiki/Paul_Martin</pm:link>
      <pm:link pm:linktype="wikipedia" pm:source="http://ne.wikipedia.org/wiki" pm:description="Wikipedia (NE)">http://ne.wikipedia.org/wiki/पावल_मार्टिन</pm:link>
      <pm:link pm:linktype="wikipedia" pm:source="http://th.wikipedia.org/wiki" pm:description="Wikipedia (TH)">http://th.wikipedia.org/wiki/พอล_มาร์ติน</pm:link>
      <pm:link pm:linktype="wikipedia" pm:source="http://vi.wikipedia.org/wiki" pm:description="Wikipedia (VI)">http://vi.wikipedia.org/wiki/Paul_Martin</pm:link>
      <pm:link pm:linktype="wikipedia" pm:source="http://pl.wikipedia.org/wiki" pm:description="Wikipedia (PL)">http://pl.wikipedia.org/wiki/Paul_Martin</pm:link>
      <pm:link pm:linktype="wikipedia" pm:source="http://yi.wikipedia.org/wiki" pm:description="Wikipedia (YI)">http://yi.wikipedia.org/wiki/פאל_מארטין</pm:link>
      <pm:link pm:linktype="wikipedia" pm:source="http://be.wikipedia.org/wiki" pm:description="Wikipedia (BE)">http://be.wikipedia.org/wiki/Пол_Эдгар_Філіп_Марцін</pm:link>
      <pm:link pm:linktype="wikipedia" pm:source="http://fr.wikipedia.org/wiki" pm:description="Wikipedia (FR)">http://fr.wikipedia.org/wiki/Paul_Martin</pm:link>
      <pm:link pm:linktype="wikipedia" pm:source="http://be-x-old.wikipedia.org/wiki" pm:description="Wikipedia (BE-X-OLD)">http://be-x-old.wikipedia.org/wiki/Пол_Мартын</pm:link>
      <pm:link pm:linktype="wikipedia" pm:source="http://uk.wikipedia.org/wiki" pm:description="Wikipedia (UK)">http://uk.wikipedia.org/wiki/Пол_Мартін</pm:link>
      <pm:link pm:linktype="wikipedia" pm:source="http://yo.wikipedia.org/wiki" pm:description="Wikipedia (YO)">http://yo.wikipedia.org/wiki/Paul_Martin</pm:link>
      <pm:link pm:linktype="wikipedia" pm:source="http://de.wikipedia.org/wiki" pm:description="Wikipedia (DE)">http://de.wikipedia.org/wiki/Paul_Martin</pm:link>
      <pm:link pm:linktype="wikipedia" pm:source="http://da.wikipedia.org/wiki" pm:description="Wikipedia (DA)">http://da.wikipedia.org/wiki/Paul_Martin_Jr.</pm:link>
      <pm:link pm:linktype="wikipedia" pm:source="http://fa.wikipedia.org/wiki" pm:description="Wikipedia (FA)">http://fa.wikipedia.org/wiki/پل_مارتین</pm:link>
      <pm:link pm:linktype="wikipedia" pm:source="http://br.wikipedia.org/wiki" pm:description="Wikipedia (BR)">http://br.wikipedia.org/wiki/Paul_Edgar_Philippe_Martin</pm:link>
      <pm:link pm:linktype="wikipedia" pm:source="http://fi.wikipedia.org/wiki" pm:description="Wikipedia (FI)">http://fi.wikipedia.org/wiki/Paul_Martin</pm:link>
      <pm:link pm:linktype="wikipedia" pm:source="http://ja.wikipedia.org/wiki" pm:description="Wikipedia (JA)">http://ja.wikipedia.org/wiki/ポール・マーティン</pm:link>
      <pm:link pm:linktype="wikipedia" pm:source="http://he.wikipedia.org/wiki" pm:description="Wikipedia (HE)">http://he.wikipedia.org/wiki/פול_מרטין</pm:link>
      <pm:link pm:linktype="wikipedia" pm:source="http://mg.wikipedia.org/wiki" pm:description="Wikipedia (MG)">http://mg.wikipedia.org/wiki/Paul_Martin</pm:link>
      <pm:link pm:linktype="wikipedia" pm:source="http://pt.wikipedia.org/wiki" pm:description="Wikipedia (PT)">http://pt.wikipedia.org/wiki/Paul_Martin</pm:link>
      <pm:link pm:linktype="wikipedia" pm:source="http://sr.wikipedia.org/wiki" pm:description="Wikipedia (SR)">http://sr.wikipedia.org/wiki/Пол_Мартин</pm:link>
      <pm:link pm:linktype="wikipedia" pm:source="http://mn.wikipedia.org/wiki" pm:description="Wikipedia (MN)">http://mn.wikipedia.org/wiki/Пол_Мартин</pm:link>
      <pm:link pm:linktype="wikipedia" pm:source="http://ko.wikipedia.org/wiki" pm:description="Wikipedia (KO)">http://ko.wikipedia.org/wiki/폴_마틴</pm:link>
      <pm:link pm:linktype="wikipedia" pm:source="http://sv.wikipedia.org/wiki" pm:description="Wikipedia (SV)">http://sv.wikipedia.org/wiki/Paul_Martin</pm:link>
      <pm:link pm:linktype="wikipedia" pm:source="http://ur.wikipedia.org/wiki" pm:description="Wikipedia (UR)">http://ur.wikipedia.org/wiki/پال_مارٹن</pm:link>
      <pm:link pm:linktype="wikipedia" pm:source="http://sh.wikipedia.org/wiki" pm:description="Wikipedia (SH)">http://sh.wikipedia.org/wiki/Paul_Martin</pm:link>
      <pm:link pm:linktype="wikipedia" pm:source="http://ms.wikipedia.org/wiki" pm:description="Wikipedia (MS)">http://ms.wikipedia.org/wiki/Paul_Martin</pm:link>
      <pm:link pm:linktype="wikipedia" pm:source="http://mr.wikipedia.org/wiki" pm:description="Wikipedia (MR)">http://mr.wikipedia.org/wiki/पॉल_मार्टिन</pm:link>
      <pm:link pm:linktype="wikipedia" pm:source="http://pdc.wikipedia.org/wiki" pm:description="Wikipedia (PDC)">http://pdc.wikipedia.org/wiki/Paul_Martin</pm:link>
      <pm:link pm:linktype="dbpedia" pm:source="http://eo.dbpedia.org/resource" pm:description="Dbpedia (EO)">http://eo.dbpedia.org/resource/Paul_Martin</pm:link>
      <pm:link pm:linktype="dbpedia" pm:source="http://zh.dbpedia.org/resource" pm:description="Dbpedia (ZH)">http://zh.dbpedia.org/resource/保罗·马丁</pm:link>
      <pm:link pm:linktype="dbpedia" pm:source="http://io.dbpedia.org/resource" pm:description="Dbpedia (IO)">http://io.dbpedia.org/resource/Paul_Martin</pm:link>
      <pm:link pm:linktype="dbpedia" pm:source="http://simple.dbpedia.org/resource" pm:description="Dbpedia (SIMPLE)">http://simple.dbpedia.org/resource/Paul_Martin_Jr.</pm:link>
      <pm:link pm:linktype="dbpedia" pm:source="http://oc.dbpedia.org/resource" pm:description="Dbpedia (OC)">http://oc.dbpedia.org/resource/Paul_Edgar_Philippe_Martin</pm:link>
      <pm:link pm:linktype="dbpedia" pm:source="http://ca.dbpedia.org/resource" pm:description="Dbpedia (CA)">http://ca.dbpedia.org/resource/Paul_Martin</pm:link>
      <pm:link pm:linktype="dbpedia" pm:source="http://it.dbpedia.org/resource" pm:description="Dbpedia (IT)">http://it.dbpedia.org/resource/Paul_Edgar_Philippe_Martin</pm:link>
      <pm:link pm:linktype="dbpedia" pm:source="http://cy.dbpedia.org/resource" pm:description="Dbpedia (CY)">http://cy.dbpedia.org/resource/Paul_Martin</pm:link>
      <pm:link pm:linktype="dbpedia" pm:source="http://gd.dbpedia.org/resource" pm:description="Dbpedia (GD)">http://gd.dbpedia.org/resource/Paul_Martin</pm:link>
      <pm:link pm:linktype="dbpedia" pm:source="http://ga.dbpedia.org/resource" pm:description="Dbpedia (GA)">http://ga.dbpedia.org/resource/Paul_Martin</pm:link>
      <pm:link pm:linktype="dbpedia" pm:source="http://cs.dbpedia.org/resource" pm:description="Dbpedia (CS)">http://cs.dbpedia.org/resource/Paul_Martin</pm:link>
      <pm:link pm:linktype="dbpedia" pm:source="http://gl.dbpedia.org/resource" pm:description="Dbpedia (GL)">http://gl.dbpedia.org/resource/Paul_Martin</pm:link>
      <pm:link pm:linktype="dbpedia" pm:source="http://id.dbpedia.org/resource" pm:description="Dbpedia (ID)">http://id.dbpedia.org/resource/Paul_Martin</pm:link>
      <pm:link pm:linktype="dbpedia" pm:source="http://es.dbpedia.org/resource" pm:description="Dbpedia (ES)">http://es.dbpedia.org/resource/Paul_Martin_(político)</pm:link>
      <pm:link pm:linktype="dbpedia" pm:source="http://ru.dbpedia.org/resource" pm:description="Dbpedia (RU)">http://ru.dbpedia.org/resource/Мартин,_Пол_Эдгар_Филип</pm:link>
      <pm:link pm:linktype="dbpedia" pm:source="http://nl.dbpedia.org/resource" pm:description="Dbpedia (NL)">http://nl.dbpedia.org/resource/Paul_Martin</pm:link>
      <pm:link pm:linktype="dbpedia" pm:source="http://pt.dbpedia.org/resource" pm:description="Dbpedia (PT)">http://pt.dbpedia.org/resource/Paul_Martin</pm:link>
      <pm:link pm:linktype="dbpedia" pm:source="http://no.dbpedia.org/resource" pm:description="Dbpedia (NO)">http://no.dbpedia.org/resource/Paul_Martin</pm:link>
      <pm:link pm:linktype="dbpedia" pm:source="http://vi.dbpedia.org/resource" pm:description="Dbpedia (VI)">http://vi.dbpedia.org/resource/Paul_Martin</pm:link>
      <pm:link pm:linktype="dbpedia" pm:source="http://pl.dbpedia.org/resource" pm:description="Dbpedia (PL)">http://pl.dbpedia.org/resource/Paul_Martin</pm:link>
      <pm:link pm:linktype="dbpedia" pm:source="http://yi.dbpedia.org/resource" pm:description="Dbpedia (YI)">http://yi.dbpedia.org/resource/פאל_מארטין</pm:link>
      <pm:link pm:linktype="dbpedia" pm:source="http://be.dbpedia.org/resource" pm:description="Dbpedia (BE)">http://be.dbpedia.org/resource/Пол_Эдгар_Філіп_Марцін</pm:link>
      <pm:link pm:linktype="dbpedia" pm:source="http://fr.dbpedia.org/resource" pm:description="Dbpedia (FR)">http://fr.dbpedia.org/resource/Paul_Martin</pm:link>
      <pm:link pm:linktype="dbpedia" pm:source="http://yo.dbpedia.org/resource" pm:description="Dbpedia (YO)">http://yo.dbpedia.org/resource/Paul_Martin</pm:link>
      <pm:link pm:linktype="dbpedia" pm:source="http://de.dbpedia.org/resource" pm:description="Dbpedia (DE)">http://de.dbpedia.org/resource/Paul_Martin</pm:link>
      <pm:link pm:linktype="dbpedia" pm:source="http://da.dbpedia.org/resource" pm:description="Dbpedia (DA)">http://da.dbpedia.org/resource/Paul_Martin_Jr.</pm:link>
      <pm:link pm:linktype="dbpedia" pm:source="http://br.dbpedia.org/resource" pm:description="Dbpedia (BR)">http://br.dbpedia.org/resource/Paul_Martin</pm:link>
      <pm:link pm:linktype="dbpedia" pm:source="http://fi.dbpedia.org/resource" pm:description="Dbpedia (FI)">http://fi.dbpedia.org/resource/Paul_Martin</pm:link>
      <pm:link pm:linktype="dbpedia" pm:source="http://ja.dbpedia.org/resource" pm:description="Dbpedia (JA)">http://ja.dbpedia.org/resource/ポール・マーティン</pm:link>
      <pm:link pm:linktype="dbpedia" pm:source="http://he.dbpedia.org/resource" pm:description="Dbpedia (HE)">http://he.dbpedia.org/resource/פול_מרטין</pm:link>
      <pm:link pm:linktype="dbpedia" pm:source="http://mg.dbpedia.org/resource" pm:description="Dbpedia (MG)">http://mg.dbpedia.org/resource/Paul_Martin</pm:link>
      <pm:link pm:linktype="dbpedia" pm:source="http://be_x_old.dbpedia.org/resource" pm:description="Dbpedia (BE_X_OLD)">http://be_x_old.dbpedia.org/resource/Пол_Мартын</pm:link>
      <pm:link pm:linktype="dbpedia" pm:source="http://nn.dbpedia.org/resource" pm:description="Dbpedia (NN)">http://nn.dbpedia.org/resource/Paul_Martin</pm:link>
      <pm:link pm:linktype="dbpedia" pm:source="http://sr.dbpedia.org/resource" pm:description="Dbpedia (SR)">http://sr.dbpedia.org/resource/Пол_Мартин</pm:link>
      <pm:link pm:linktype="dbpedia" pm:source="http://mn.dbpedia.org/resource" pm:description="Dbpedia (MN)">http://mn.dbpedia.org/resource/Пол_Мартин</pm:link>
      <pm:link pm:linktype="dbpedia" pm:source="http://ko.dbpedia.org/resource" pm:description="Dbpedia (KO)">http://ko.dbpedia.org/resource/폴_마틴</pm:link>
      <pm:link pm:linktype="dbpedia" pm:source="http://sv.dbpedia.org/resource" pm:description="Dbpedia (SV)">http://sv.dbpedia.org/resource/Paul_Martin</pm:link>
      <pm:link pm:linktype="dbpedia" pm:source="http://ur.dbpedia.org/resource" pm:description="Dbpedia (UR)">http://ur.dbpedia.org/resource/پال_مارٹن</pm:link>
      <pm:link pm:linktype="dbpedia" pm:source="http://sh.dbpedia.org/resource" pm:description="Dbpedia (SH)">http://sh.dbpedia.org/resource/Paul_Martin</pm:link>
      <pm:link pm:linktype="dbpedia" pm:source="http://uk.dbpedia.org/resource" pm:description="Dbpedia (UK)">http://uk.dbpedia.org/resource/Пол_Мартін</pm:link>
      <pm:link pm:linktype="dbpedia" pm:source="http://mr.dbpedia.org/resource" pm:description="Dbpedia (MR)">http://mr.dbpedia.org/resource/पॉल_मार्टिन</pm:link>
      <pm:link pm:linktype="dbpedia" pm:source="http://pdc.dbpedia.org/resource" pm:description="Dbpedia (PDC)">http://pdc.dbpedia.org/resource/Paul_Martin</pm:link>
    </pm:links>
    <pm:memberships>
      <pm:membership pm:body="commons" pm:district="LaSalle--Émard" openpx:province="Quebec">
        <pm:period pm:from="2006-01-23" pm:from-granularity="8" pm:till="2008-09-07" pm:till-granularity="8"/>
      </pm:membership>
      <pm:membership pm:body="commons" pm:district="LaSalle--Émard" openpx:province="Quebec">
        <pm:period pm:from="2004-06-28" pm:from-granularity="8" pm:till="2005-11-29" pm:till-granularity="8"/>
      </pm:membership>
      <pm:membership pm:body="commons" pm:district="LaSalle--Émard" openpx:province="Quebec">
        <pm:period pm:from="2000-11-27" pm:from-granularity="8" pm:till="2004-05-23" pm:till-granularity="8"/>
      </pm:membership>
      <pm:membership pm:body="commons" pm:district="LaSalle--Émard" openpx:province="Quebec">
        <pm:period pm:from="1997-06-02" pm:from-granularity="8" pm:till="2000-10-22" pm:till-granularity="8"/>
      </pm:membership>
      <pm:membership pm:body="commons" pm:district="LaSalle--Émard" openpx:province="Quebec">
        <pm:period pm:from="1993-10-25" pm:from-granularity="8" pm:till="1997-04-27" pm:till-granularity="8"/>
      </pm:membership>
      <pm:membership pm:body="commons" pm:district="LaSalle--Émard" openpx:province="Quebec">
        <pm:period pm:from="1988-11-21" pm:from-granularity="8" pm:till="1993-09-08" pm:till-granularity="8"/>
      </pm:membership>
      <pm:membership pm:body="government">
        <pm:period pm:from="2003-12-12" pm:from-granularity="8" pm:till="2006-02-05" pm:till-granularity="8"/>
        <pm:name>Prime Minister</pm:name>
      </pm:membership>
      <pm:membership pm:body="government">
        <pm:period pm:from="1993-11-04" pm:from-granularity="8" pm:till="1996-01-24" pm:till-granularity="8"/>
        <pm:name>Minister responsible for the Federal Office of Regional Development - Quebec</pm:name>
      </pm:membership>
      <pm:membership pm:body="government">
        <pm:period pm:from="1993-11-04" pm:from-granularity="8" pm:till="2002-06-01" pm:till-granularity="8"/>
        <pm:name>Minister of Finance</pm:name>
      </pm:membership>
      <pm:membership pm:party-name="Liberal" pm:party-ref="ca.p.liberal" pm:body="other">
        <pm:period pm:from="1988-11-21" pm:from-granularity="8" pm:till="2008-10-13" pm:till-granularity="8"/>
      </pm:membership>
    </pm:memberships>
    <pm:biographies>
      <pm:biography pm:source="http://dbpedia.org/page/Paul_Martin">Paul Edgar Philippe Martin PC CC (born August 28, 1938), also known as Paul Martin, Jr., is a Canadian politician who was the 21st Prime Minister of Canada and leader of the Liberal Party of Canada after being the Canadian Minister of Finance.On November 14, 2003, Martin succeeded Jean Chrétien as leader of the Liberal Party and became prime minister on December 12, 2003. After the 2004 election, his Liberal Party retained power, though it was reduced to a minority government. Forced by a confidence vote, the 2006 general election produced a minority government for the opposition Conservative Party, making Stephen Harper prime minister. Martin stepped down as parliamentary leader after the election, handing the reins to Bill Graham for the interim. Martin stayed on as party leader until he resigned on March 18, being eventually succeeded by Stephane Dion.Martin served as the Member of Parliament for the riding of LaSalle—Émard in Montreal from his election in the 1988 election to his retirement in 2008. He served as Minister of Finance from 1993 to 2002. He oversaw many changes in the financial structure of the Canadian government, and his policies had a direct effect on eliminating the country's chronic fiscal deficit by reforming various programs including social services.Now seen as a global diplomat, Martin continues to contribute on the international arena through a variety of initiatives such as Incentives for Global Health, the not-for-profit behind the Health Impact Fund, where he serves as a member of the Advisory Board.</pm:biography>
    </pm:biographies>
  </pm:member>
</root>
