<root xmlns:owl="http://www.w3.org/2002/07/owl#" xmlns:pmx="http://www.politicalmashup.nl/extra" xmlns:dc="http://purl.org/dc/elements/1.1/" xmlns:pmd="http://www.politicalmashup.nl/docinfo" xmlns:openpx="https://openparliament.ca/extra" xmlns:dcterms="http://purl.org/dc/terms/" xmlns:html="http://www.w3.org/1999/xhtml" xmlns:rdf="http://www.w3.org/1999/02/22-rdf-syntax-ns#" xmlns:xsd="http://www.w3.org/2001/XMLSchema-datatypes" xmlns:xsi="http://www.w3.org/2001/XMLSchema-instance" xmlns:pm="http://www.politicalmashup.nl">
  <pmd:docinfo>
    <pm:comment>Data is valid with respect to the Relax NG schema http://schema.politicalmashup.nl/memberX.html. This is the open version of http://schema.politicalmashup.nl/member.html</pm:comment>
  </pmd:docinfo>
  <meta pm:id="ca.m.468">
    <dc:identifier/>
    <dc:format>text/xml</dc:format>
    <dc:type>Members</dc:type>
    <dc:contributor>http://www.politicalmashup.nl</dc:contributor>
    <dc:coverage>
      <country dcterms:ISO3166-1="CA">Canada</country>
    </dc:coverage>
    <dc:creator>http://dilipad.history.ac.uk</dc:creator>
    <dc:language>
      <pm:language dcterms:ISO639-2="eng">English</pm:language>
    </dc:language>
    <dc:publisher>http://www.parl.gc.ca/parlinfo/</dc:publisher>
    <dc:rights>http://www.parl.gc.ca/parlinfo/</dc:rights>
    <dc:date>2015-06-29+01:00</dc:date>
    <dc:title>NOWLAN, The Hon. George Clyde, P.C., Q.C.,  B.A., LL.B.</dc:title>
    <dc:description>Member information for: NOWLAN, The Hon. George Clyde, P.C., Q.C.,  B.A., LL.B.</dc:description>
    <dc:source>
      <dc:source pm:used-source="true">
        <pm:link pm:linktype="trusted" pm:source="http://www.parl.gc.ca/parlinfo">http://www.parl.gc.ca/parlinfo</pm:link>
      </dc:source>
      <dc:source pm:used-source="true">
        <pm:link pm:linktype="trusted" pm:source="http://www.parl.gc.ca/ParlInfo/Files/Parliamentarian.aspx?Item=ea30e79d-1feb-461a-bbea-b3e5a570ee30&amp;Language=E&amp;Section=ALL">http://www.parl.gc.ca/ParlInfo/Files/Parliamentarian.aspx?Item=ea30e79d-1feb-461a-bbea-b3e5a570ee30&amp;Language=E&amp;Section=ALL</pm:link>
      </dc:source>
    </dc:source>
    <dc:subject/>
    <dc:relation>All pm:party-ref attributes appearing in http://www.politicalmashup.nl documents refer to http://resolver.politicalmashup.nl/[pm:party-ref] .</dc:relation>
  </meta>
  <pm:member pm:id="ca.m.468">
    <pm:name>
      <pm:full>NOWLAN, The Hon. George Clyde, P.C., Q.C.,  B.A., LL.B.</pm:full>
      <pm:first>George Clyde</pm:first>
      <pm:last>Nowlan</pm:last>
      <pm:titles>
        <pm:title pm:position="prefix" pm:honorific="honorary">The Hon.</pm:title>
        <pm:title pm:position="suffix" pm:honorific="academic">P.C.</pm:title>
        <pm:title pm:position="suffix" pm:honorific="academic">Q.C.</pm:title>
        <pm:title pm:position="suffix" pm:honorific="academic">B.A.</pm:title>
        <pm:title pm:position="suffix" pm:honorific="academic">LL.B.</pm:title>
      </pm:titles>
    </pm:name>
    <pm:personal>
      <pm:born pm:date="1898-08-14" pm:granularity="8" pm:place="Havelock, Nova Scotia, Canada"/>
      <pm:deceased pm:date="1965-05-31" pm:granularity="8"/>
      <pm:gender>male</pm:gender>
    </pm:personal>
    <pm:curriculum>
      <pm:extra-curricular pm:source="http://www.parl.gc.ca/parlinfo/">
        <pm:name>Barrister, lawyer</pm:name>
      </pm:extra-curricular>
    </pm:curriculum>
    <pm:links>
      <pm:link pm:linktype="trusted" pm:source="http://www.parl.gc.ca/parlinfo" pm:description="Parlinfo">http://www.parl.gc.ca/ParlInfo/Files/Parliamentarian.aspx?Item=ea30e79d-1feb-461a-bbea-b3e5a570ee30&amp;Language=E&amp;Section=ALL</pm:link>
      <pm:link pm:linktype="photo" pm:source="http://www.parl.gc.ca/parlinfo" pm:description="Portrait photo Parlinfo">http://www.parl.gc.ca/parlinfo/images/Picture.aspx?Item=54bac65c-bd4c-43da-bcbf-e9ba06136998</pm:link>
      <pm:link pm:linktype="dbpedia" pm:source="http://dbpedia.org" pm:description="Dbpedia ()">http://dbpedia.org/resource/George_Nowlan</pm:link>
      <pm:link pm:linktype="wikipedia" pm:source="http://en.wikipedia.org" pm:description="Wikipedia (EN)">http://en.wikipedia.org/wiki/George_Nowlan</pm:link>
    </pm:links>
    <pm:memberships>
      <pm:membership pm:body="commons" pm:district="Digby--Annapolis--Kings" openpx:province="Nova Scotia">
        <pm:period pm:from="1963-04-08" pm:from-granularity="8" pm:till="1965-09-08" pm:till-granularity="8"/>
      </pm:membership>
      <pm:membership pm:body="commons" pm:district="Digby--Annapolis--Kings" openpx:province="Nova Scotia">
        <pm:period pm:from="1962-06-18" pm:from-granularity="8" pm:till="1963-02-06" pm:till-granularity="8"/>
      </pm:membership>
      <pm:membership pm:body="commons" pm:district="Digby--Annapolis--Kings" openpx:province="Nova Scotia">
        <pm:period pm:from="1958-03-31" pm:from-granularity="8" pm:till="1962-04-19" pm:till-granularity="8"/>
      </pm:membership>
      <pm:membership pm:body="commons" pm:district="Digby--Annapolis--Kings" openpx:province="Nova Scotia">
        <pm:period pm:from="1957-06-10" pm:from-granularity="8" pm:till="1958-02-01" pm:till-granularity="8"/>
      </pm:membership>
      <pm:membership pm:body="commons" pm:district="Digby--Annapolis--Kings" openpx:province="Nova Scotia">
        <pm:period pm:from="1953-08-10" pm:from-granularity="8" pm:till="1957-04-12" pm:till-granularity="8"/>
      </pm:membership>
      <pm:membership pm:body="commons" pm:district="Annapolis--Kings" openpx:province="Nova Scotia">
        <pm:period pm:from="1950-06-19" pm:from-granularity="8" pm:till="1953-06-13" pm:till-granularity="8"/>
      </pm:membership>
      <pm:membership pm:body="commons" pm:district="Digby--Annapolis--Kings" openpx:province="Nova Scotia">
        <pm:period pm:from="1948-12-13" pm:from-granularity="8" pm:till="1949-04-30" pm:till-granularity="8"/>
      </pm:membership>
      <pm:membership pm:body="government">
        <pm:period pm:from="1962-08-09" pm:from-granularity="8" pm:till="1963-04-21" pm:till-granularity="8"/>
        <pm:name>Minister of Finance and Receiver General</pm:name>
      </pm:membership>
      <pm:membership pm:body="government">
        <pm:period pm:from="1957-06-21" pm:from-granularity="8" pm:till="1962-08-08" pm:till-granularity="8"/>
        <pm:name>Minister of National Revenue</pm:name>
      </pm:membership>
    <pm:membership pm:party-name="Progressive Conservative" pm:party-ref="ca.p.progressiveconservative" pm:body="other">
        <pm:period pm:from="1950-06-19" pm:from-granularity="8" pm:till="1965-05-31" pm:till-granularity="8"/>
      </pm:membership>
      <pm:membership pm:party-name="Progressive Conservative" pm:party-ref="ca.p.progressiveconservative" pm:body="other">
        <pm:period pm:from="1948-12-13" pm:from-granularity="8" pm:till="1949-06-26" pm:till-granularity="8"/>
      </pm:membership>
    </pm:memberships>
    <pm:biographies>
      <pm:biography pm:source="http://dbpedia.org/page/George_Nowlan">George Clyde Nowlan, PC (14 September 1898 – 31 May 1965) was a Canadian member of Parliament and Cabinet Minister. A member of the Progressive Conservative Party of Canada, he served from 9 August 1962–21 April 1963 as the Minister of Finance in the administration of John Diefenbaker, and was also responsible for the CBC.In addition to serving as an MP, Nowlan was a soldier in the Canadian Expeditionary Force during the First World War. After the war ended, he returned to the Annapolis Valley of Nova Scotia and attended Acadia University to study for a BA, graduating in 1920. He then studied law at Dalhousie University.Nowlan was an MLA in the Nova Scotia Legislature in the 1920s, and was always known for his reputation as a hard worker and a Party Man. He served a term as the Progressive Conservative Party's president. While serving as Minister of National Revenue in 1962, he forbid Customs to censor or ban entrance to any publication unless a Canadian court had already ruled it to be "obscene", rather than using their own discretion. Five years later, this was overturned.Disagreements between Nowlan and Diefenbaker are widely believed to have been at the heart of the PC government, allowing it to be reduced to a minority government in the 1962 federal election and then defeated a year later by a vote of no confidence by Lester Pearson and the Liberal Party in the 1963 election.His son Pat Nowlan later became a Progressive Conservative (and later Independent Progressive Conservative) MP in Nowlan's riding of Kings County.</pm:biography>
    </pm:biographies>
  </pm:member>
</root>
