<root xmlns:owl="http://www.w3.org/2002/07/owl#" xmlns:pmx="http://www.politicalmashup.nl/extra" xmlns:dc="http://purl.org/dc/elements/1.1/" xmlns:pmd="http://www.politicalmashup.nl/docinfo" xmlns:openpx="https://openparliament.ca/extra" xmlns:dcterms="http://purl.org/dc/terms/" xmlns:html="http://www.w3.org/1999/xhtml" xmlns:rdf="http://www.w3.org/1999/02/22-rdf-syntax-ns#" xmlns:xsd="http://www.w3.org/2001/XMLSchema-datatypes" xmlns:xsi="http://www.w3.org/2001/XMLSchema-instance" xmlns:pm="http://www.politicalmashup.nl">
  <pmd:docinfo>
    <pm:comment>Data is valid with respect to the Relax NG schema http://schema.politicalmashup.nl/memberX.html. This is the open version of http://schema.politicalmashup.nl/member.html</pm:comment>
  </pmd:docinfo>
  <meta pm:id="ca.m.2127">
    <dc:identifier/>
    <dc:format>text/xml</dc:format>
    <dc:type>Members</dc:type>
    <dc:contributor>http://www.politicalmashup.nl</dc:contributor>
    <dc:coverage>
      <country dcterms:ISO3166-1="CA">Canada</country>
    </dc:coverage>
    <dc:creator>http://dilipad.history.ac.uk</dc:creator>
    <dc:language>
      <pm:language dcterms:ISO639-2="eng">English</pm:language>
    </dc:language>
    <dc:publisher>http://www.parl.gc.ca/parlinfo/</dc:publisher>
    <dc:rights>http://www.parl.gc.ca/parlinfo/</dc:rights>
    <dc:date>2015-06-30+01:00</dc:date>
    <dc:title>BREITHAUPT, The Hon. Louis Orville</dc:title>
    <dc:description>Member information for: BREITHAUPT, The Hon. Louis Orville</dc:description>
    <dc:source>
      <dc:source pm:used-source="true">
        <pm:link pm:linktype="trusted" pm:source="http://www.parl.gc.ca/parlinfo">http://www.parl.gc.ca/parlinfo</pm:link>
      </dc:source>
      <dc:source pm:used-source="true">
        <pm:link pm:linktype="trusted" pm:source="http://www.parl.gc.ca/ParlInfo/Files/Parliamentarian.aspx?Item=20aac5fd-8bbd-4322-8271-04cec9426984&amp;Language=E&amp;Section=ALL">http://www.parl.gc.ca/ParlInfo/Files/Parliamentarian.aspx?Item=20aac5fd-8bbd-4322-8271-04cec9426984&amp;Language=E&amp;Section=ALL</pm:link>
      </dc:source>
    </dc:source>
    <dc:subject/>
    <dc:relation>All pm:party-ref attributes appearing in http://www.politicalmashup.nl documents refer to http://resolver.politicalmashup.nl/[pm:party-ref] .</dc:relation>
  </meta>
  <pm:member pm:id="ca.m.2127">
    <pm:name>
      <pm:full>BREITHAUPT, The Hon. Louis Orville</pm:full>
      <pm:first>Louis Orville</pm:first>
      <pm:last>Breithaupt</pm:last>
      <pm:titles>
        <pm:title pm:position="prefix" pm:honorific="honorary">The Hon.</pm:title>
      </pm:titles>
    </pm:name>
    <pm:personal>
      <pm:born pm:date="1890-10-28" pm:granularity="8" pm:place="Berlin (Kitchener), Ontario, Canada"/>
      <pm:deceased pm:date="1960-12-06" pm:granularity="8"/>
      <pm:gender>male</pm:gender>
    </pm:personal>
    <pm:curriculum>
      <pm:extra-curricular pm:source="http://www.parl.gc.ca/parlinfo/">
        <pm:name>Manufacturer</pm:name>
      </pm:extra-curricular>
    </pm:curriculum>
    <pm:links>
      <pm:link pm:linktype="trusted" pm:source="http://www.parl.gc.ca/parlinfo" pm:description="Parlinfo">http://www.parl.gc.ca/ParlInfo/Files/Parliamentarian.aspx?Item=20aac5fd-8bbd-4322-8271-04cec9426984&amp;Language=E&amp;Section=ALL</pm:link>
      <pm:link pm:linktype="photo" pm:source="http://www.parl.gc.ca/parlinfo" pm:description="Portrait photo Parlinfo">http://www.parl.gc.ca/parlinfo/images/Picture.aspx?Item=6124a584-8b56-466d-aead-982d957326e4</pm:link>
      <pm:link pm:linktype="dbpedia" pm:source="http://dbpedia.org" pm:description="Dbpedia ()">http://dbpedia.org/resource/Louis_Orville_Breithaupt</pm:link>
      <pm:link pm:linktype="wikipedia" pm:source="http://en.wikipedia.org" pm:description="Wikipedia (EN)">http://en.wikipedia.org/wiki/Louis_Orville_Breithaupt</pm:link>
    </pm:links>
    <pm:memberships>
      <pm:membership pm:body="commons" pm:district="Waterloo North" openpx:province="Ontario">
        <pm:period pm:from="1949-06-27" pm:from-granularity="8" pm:till="1953-06-13" pm:till-granularity="8"/>
      </pm:membership>
      <pm:membership pm:body="commons" pm:district="Waterloo North" openpx:province="Ontario">
        <pm:period pm:from="1945-06-11" pm:from-granularity="8" pm:till="1949-04-30" pm:till-granularity="8"/>
      </pm:membership>
      <pm:membership pm:body="commons" pm:district="Waterloo North" openpx:province="Ontario">
        <pm:period pm:from="1940-08-19" pm:from-granularity="8" pm:till="1945-04-16" pm:till-granularity="8"/>
      </pm:membership>
    <pm:membership pm:party-name="Liberal" pm:party-ref="ca.p.liberal" pm:body="other">
        <pm:period pm:from="1940-08-19" pm:from-granularity="8" pm:till="1952-01-22" pm:till-granularity="8"/>
      </pm:membership>
    </pm:memberships>
    <pm:biographies>
      <pm:biography pm:source="http://dbpedia.org/page/Louis_Orville_Breithaupt">Louis Orville Breithaupt (October 28, 1890 – December 12, 1960) served as the 18th Lieutenant Governor of Ontario, Canada, from 1952 to 1957.Born in Berlin (later Kitchener), Ontario, the son of Louis Jacob Breithaupt and Emma Alvarine Devitt, he was educated at the University of Toronto. He became head of his family's leather business, Breithaupt Leather Company, in Kitchener. He was a Kitchener alderman for four years, and in 1923 became the youngest mayor in the city's history. He was a Liberal Member of Parliament from 1940 to 1952.Breithaupt was appointed Lieutenant Governor of Ontario in 1952 and served until 1957.In 1953, he was awarded an honorary LL.D from McMaster University.Breithaupt was active in many service organizations, such as the YMCA and Rotary Club. In 1959, he became Chancellor of Victoria University. Breithaupt died in Toronto in 1960 at the age of 70.</pm:biography>
    </pm:biographies>
  </pm:member>
</root>
