<root xmlns:owl="http://www.w3.org/2002/07/owl#" xmlns:pmx="http://www.politicalmashup.nl/extra" xmlns:dc="http://purl.org/dc/elements/1.1/" xmlns:pmd="http://www.politicalmashup.nl/docinfo" xmlns:openpx="https://openparliament.ca/extra" xmlns:dcterms="http://purl.org/dc/terms/" xmlns:html="http://www.w3.org/1999/xhtml" xmlns:rdf="http://www.w3.org/1999/02/22-rdf-syntax-ns#" xmlns:xsd="http://www.w3.org/2001/XMLSchema-datatypes" xmlns:xsi="http://www.w3.org/2001/XMLSchema-instance" xmlns:pm="http://www.politicalmashup.nl">
  <pmd:docinfo>
    <pm:comment>Data is valid with respect to the Relax NG schema http://schema.politicalmashup.nl/memberX.html. This is the open version of http://schema.politicalmashup.nl/member.html</pm:comment>
  </pmd:docinfo>
  <meta pm:id="ca.m.2697">
    <dc:identifier/>
    <dc:format>text/xml</dc:format>
    <dc:type>Members</dc:type>
    <dc:contributor>http://www.politicalmashup.nl</dc:contributor>
    <dc:coverage>
      <country dcterms:ISO3166-1="CA">Canada</country>
    </dc:coverage>
    <dc:creator>http://dilipad.history.ac.uk</dc:creator>
    <dc:language>
      <pm:language dcterms:ISO639-2="eng">English</pm:language>
    </dc:language>
    <dc:publisher>http://www.parl.gc.ca/parlinfo/</dc:publisher>
    <dc:rights>http://www.parl.gc.ca/parlinfo/</dc:rights>
    <dc:date>2015-08-07+01:00</dc:date>
    <dc:title>MCCARTHY, The Hon. Leighton Goldie, P.C., K.C.</dc:title>
    <dc:description>Member information for: MCCARTHY, The Hon. Leighton Goldie, P.C., K.C.</dc:description>
    <dc:source>
      <dc:source pm:used-source="true">
        <pm:link pm:linktype="trusted" pm:source="http://www.parl.gc.ca/parlinfo">http://www.parl.gc.ca/parlinfo</pm:link>
      </dc:source>
      <dc:source pm:used-source="true">
        <pm:link pm:linktype="trusted" pm:source="http://www.parl.gc.ca/ParlInfo/Files/Parliamentarian.aspx?Item=445fafe5-f605-4932-84a1-bae1a19dd968&amp;Language=E&amp;Section=ALL">http://www.parl.gc.ca/ParlInfo/Files/Parliamentarian.aspx?Item=445fafe5-f605-4932-84a1-bae1a19dd968&amp;Language=E&amp;Section=ALL</pm:link>
      </dc:source>
    </dc:source>
    <dc:subject/>
    <dc:relation>All pm:party-ref attributes appearing in http://www.politicalmashup.nl documents refer to http://resolver.politicalmashup.nl/[pm:party-ref] .</dc:relation>
  </meta>
  <pm:member pm:id="ca.m.2697">
    <pm:name>
      <pm:full>MCCARTHY, The Hon. Leighton Goldie, P.C., K.C.</pm:full>
      <pm:first>Leighton Goldie</pm:first>
      <pm:last>McCarthy</pm:last>
      <pm:titles>
        <pm:title pm:position="prefix" pm:honorific="honorary">The Hon.</pm:title>
        <pm:title pm:position="suffix" pm:honorific="academic">P.C.</pm:title>
        <pm:title pm:position="suffix" pm:honorific="academic">K.C.</pm:title>
      </pm:titles>
    </pm:name>
    <pm:personal>
      <pm:born pm:date="1869-12-15" pm:granularity="8" pm:place="Walkerton, Ontario, Canada"/>
      <pm:deceased pm:date="1952-10-03" pm:granularity="8"/>
      <pm:gender>male</pm:gender>
    </pm:personal>
    <pm:curriculum>
      <pm:extra-curricular pm:source="http://www.parl.gc.ca/parlinfo/">
        <pm:name>Ambassador, lawyer</pm:name>
      </pm:extra-curricular>
    </pm:curriculum>
    <pm:links>
      <pm:link pm:linktype="trusted" pm:source="http://www.parl.gc.ca/parlinfo" pm:description="Parlinfo">http://www.parl.gc.ca/ParlInfo/Files/Parliamentarian.aspx?Item=445fafe5-f605-4932-84a1-bae1a19dd968&amp;Language=E&amp;Section=ALL</pm:link>
      <pm:link pm:linktype="photo" pm:source="http://www.parl.gc.ca/parlinfo" pm:description="Portrait photo Parlinfo">http://www.parl.gc.ca/parlinfo/images/Picture.aspx?Item=9c9a3a2b-7dd8-4961-a7e0-46d85057f1a8</pm:link>
      <pm:link pm:linktype="dbpedia" pm:source="http://dbpedia.org" pm:description="Dbpedia ()">http://dbpedia.org/resource/Leighton_McCarthy</pm:link>
      <pm:link pm:linktype="wikipedia" pm:source="http://en.wikipedia.org" pm:description="Wikipedia (EN)">http://en.wikipedia.org/wiki/Leighton_McCarthy</pm:link>
    </pm:links>
    <pm:memberships>
      <pm:membership pm:body="commons" pm:district="Simcoe North" openpx:province="Ontario">
        <pm:period pm:from="1904-11-03" pm:from-granularity="8" pm:till="1908-09-17" pm:till-granularity="8"/>
      </pm:membership>
      <pm:membership pm:body="commons" pm:district="Simcoe North" openpx:province="Ontario">
        <pm:period pm:from="1900-11-07" pm:from-granularity="8" pm:till="1904-09-29" pm:till-granularity="8"/>
      </pm:membership>
      <pm:membership pm:body="commons" pm:district="Simcoe North" openpx:province="Ontario">
        <pm:period pm:from="1898-12-14" pm:from-granularity="8" pm:till="1900-10-09" pm:till-granularity="8"/>
      </pm:membership>
    <pm:membership pm:party-name="Independent" pm:party-ref="not-avaible" pm:body="other">
        <pm:period pm:from="1898-12-14" pm:from-granularity="8" pm:till="1911-09-20" pm:till-granularity="8"/>
      </pm:membership>
    </pm:memberships>
    <pm:biographies>
      <pm:biography pm:source="http://dbpedia.org/page/Leighton_McCarthy">Leighton Goldie McCarthy, PC (December 15, 1869 – October 3, 1952) was a Canadian politician and diplomat.Born in Walkerton, Ontario, he was elected to the Canadian House of Commons in 1898 as an Independent (McCarthyite candidates 1896) representing the riding of Simcoe North. He was re-elected in 1900 and 1904. He was defeated in 1911 when he ran as a Liberal. He was President of the Canada Life Assurance Company. In 1941, he was appointed to the Queen's Privy Council for Canada. From 1941 to 1944, he was the first Canadian ambassador to the United States (before the position was called Envoy Extraordinary and Minister Plenipotentiary).</pm:biography>
    </pm:biographies>
  </pm:member>
</root>
