<root xmlns:owl="http://www.w3.org/2002/07/owl#" xmlns:pmx="http://www.politicalmashup.nl/extra" xmlns:dc="http://purl.org/dc/elements/1.1/" xmlns:pmd="http://www.politicalmashup.nl/docinfo" xmlns:openpx="https://openparliament.ca/extra" xmlns:dcterms="http://purl.org/dc/terms/" xmlns:html="http://www.w3.org/1999/xhtml" xmlns:rdf="http://www.w3.org/1999/02/22-rdf-syntax-ns#" xmlns:xsd="http://www.w3.org/2001/XMLSchema-datatypes" xmlns:xsi="http://www.w3.org/2001/XMLSchema-instance" xmlns:pm="http://www.politicalmashup.nl">
  <pmd:docinfo>
    <pm:comment>Data is valid with respect to the Relax NG schema http://schema.politicalmashup.nl/memberX.html. This is the open version of http://schema.politicalmashup.nl/member.html</pm:comment>
  </pmd:docinfo>
  <meta pm:id="ca.m.2450">
    <dc:identifier/>
    <dc:format>text/xml</dc:format>
    <dc:type>Members</dc:type>
    <dc:contributor>http://www.politicalmashup.nl</dc:contributor>
    <dc:coverage>
      <country dcterms:ISO3166-1="CA">Canada</country>
    </dc:coverage>
    <dc:creator>http://dilipad.history.ac.uk</dc:creator>
    <dc:language>
      <pm:language dcterms:ISO639-2="eng">English</pm:language>
    </dc:language>
    <dc:publisher>http://www.parl.gc.ca/parlinfo/</dc:publisher>
    <dc:rights>http://www.parl.gc.ca/parlinfo/</dc:rights>
    <dc:date>2015-06-30+01:00</dc:date>
    <dc:title>MITCHELL, The Hon. Humphrey, P.C.</dc:title>
    <dc:description>Member information for: MITCHELL, The Hon. Humphrey, P.C.</dc:description>
    <dc:source>
      <dc:source pm:used-source="true">
        <pm:link pm:linktype="trusted" pm:source="http://www.parl.gc.ca/parlinfo">http://www.parl.gc.ca/parlinfo</pm:link>
      </dc:source>
      <dc:source pm:used-source="true">
        <pm:link pm:linktype="trusted" pm:source="http://www.parl.gc.ca/ParlInfo/Files/Parliamentarian.aspx?Item=48fe0415-1454-43d8-a242-1562dedacc97&amp;Language=E&amp;Section=ALL">http://www.parl.gc.ca/ParlInfo/Files/Parliamentarian.aspx?Item=48fe0415-1454-43d8-a242-1562dedacc97&amp;Language=E&amp;Section=ALL</pm:link>
      </dc:source>
    </dc:source>
    <dc:subject/>
    <dc:relation>All pm:party-ref attributes appearing in http://www.politicalmashup.nl documents refer to http://resolver.politicalmashup.nl/[pm:party-ref] .</dc:relation>
  </meta>
  <pm:member pm:id="ca.m.2450">
    <pm:name>
      <pm:full>MITCHELL, The Hon. Humphrey, P.C.</pm:full>
      <pm:first>Humphrey</pm:first>
      <pm:last>Mitchell</pm:last>
      <pm:titles>
        <pm:title pm:position="prefix" pm:honorific="honorary">The Hon.</pm:title>
        <pm:title pm:position="suffix" pm:honorific="academic">P.C.</pm:title>
      </pm:titles>
    </pm:name>
    <pm:personal>
      <pm:born pm:date="1894-09-09" pm:granularity="8" pm:place="Old Shoreham, Sussex, England"/>
      <pm:deceased pm:date="1950-08-01" pm:granularity="8"/>
      <pm:gender>male</pm:gender>
    </pm:personal>
    <pm:curriculum>
      <pm:extra-curricular pm:source="http://www.parl.gc.ca/parlinfo/">
        <pm:name>Machine operator, union officer</pm:name>
      </pm:extra-curricular>
    </pm:curriculum>
    <pm:links>
      <pm:link pm:linktype="trusted" pm:source="http://www.parl.gc.ca/parlinfo" pm:description="Parlinfo">http://www.parl.gc.ca/ParlInfo/Files/Parliamentarian.aspx?Item=48fe0415-1454-43d8-a242-1562dedacc97&amp;Language=E&amp;Section=ALL</pm:link>
      <pm:link pm:linktype="photo" pm:source="http://www.parl.gc.ca/parlinfo" pm:description="Portrait photo Parlinfo">http://www.parl.gc.ca/parlinfo/images/Picture.aspx?Item=c36522b6-3706-4c8f-9929-f5d5da2865cc</pm:link>
      <pm:link pm:linktype="dbpedia" pm:source="http://dbpedia.org" pm:description="Dbpedia ()">http://dbpedia.org/resource/Humphrey_Mitchell</pm:link>
      <pm:link pm:linktype="wikipedia" pm:source="http://en.wikipedia.org" pm:description="Wikipedia (EN)">http://en.wikipedia.org/wiki/Humphrey_Mitchell</pm:link>
      <pm:link pm:linktype="wikipedia" pm:source="http://de.wikipedia.org/wiki" pm:description="Wikipedia (DE)">http://de.wikipedia.org/wiki/Humphrey_Mitchell</pm:link>
    </pm:links>
    <pm:memberships>
      <pm:membership pm:body="commons" pm:district="Welland" openpx:province="Ontario">
        <pm:period pm:from="1949-06-27" pm:from-granularity="8" pm:till="1953-06-13" pm:till-granularity="8"/>
      </pm:membership>
      <pm:membership pm:body="commons" pm:district="Welland" openpx:province="Ontario">
        <pm:period pm:from="1945-06-11" pm:from-granularity="8" pm:till="1949-04-30" pm:till-granularity="8"/>
      </pm:membership>
      <pm:membership pm:body="commons" pm:district="Welland" openpx:province="Ontario">
        <pm:period pm:from="1942-02-09" pm:from-granularity="8" pm:till="1945-04-16" pm:till-granularity="8"/>
      </pm:membership>
      <pm:membership pm:body="commons" pm:district="Hamilton East" openpx:province="Ontario">
        <pm:period pm:from="1931-08-10" pm:from-granularity="8" pm:till="1935-08-14" pm:till-granularity="8"/>
      </pm:membership>
      <pm:membership pm:body="government">
        <pm:period pm:from="1948-11-15" pm:from-granularity="8" pm:till="1950-08-01" pm:till-granularity="8"/>
        <pm:name>Minister of Labour</pm:name>
      </pm:membership>
      <pm:membership pm:body="government">
        <pm:period pm:from="1941-12-15" pm:from-granularity="8" pm:till="1948-11-15" pm:till-granularity="8"/>
        <pm:name>Minister of Labour</pm:name>
      </pm:membership>
    <pm:membership pm:party-name="Liberal" pm:party-ref="ca.p.liberal" pm:body="other">
        <pm:period pm:from="1942-02-09" pm:from-granularity="8" pm:till="1950-08-01" pm:till-granularity="8"/>
      </pm:membership>
      <pm:membership pm:party-name="Labour" pm:party-ref="ca.p.Lab" pm:body="other">
        <pm:period pm:from="1931-08-10" pm:from-granularity="8" pm:till="1935-10-13" pm:till-granularity="8"/>
      </pm:membership>
    </pm:memberships>
    <pm:biographies>
      <pm:biography pm:source="http://dbpedia.org/page/Humphrey_Mitchell">Humphrey Mitchell, PC (September 9, 1894 – August 1, 1950) was a Canadian politician and trade unionist.A land surveyor employed with Hamilton Hydro, Mitchell was active with the union movement in the city. Upon the death of Hamilton East's Conservative Member of Parliament (MP), George Septimus Rennie in 1931, Mitchell was approached to run in the by-election to fill the seat as a Labour candidate. Hamilton East was a strong working class riding that had elected Labour candidates to the Legislative Assembly of Ontario and to city council.The Liberals, in opposition having lost the previous year's general election did not run a candidate against Mitchell in order to avoid dividing the anti-Conservative vote. Given future events, it is also possible the Liberals believed that Mitchell would support the Liberal Party unofficially if elected.Mitchell won the by-election, and entered the Canadian House of Commons. He did not get along well with the rump of Independent Labour MPs led informally by J.S. Woodsworth and referred to as the "Ginger Group". While Mitchell attended the "founding meeting" of the Co-operative Commonwealth Federation in William Irvine's office, he refused to join the new party when Labour MPs joined with farmers groups, socialist groups and others to officially launch the CCF in 1932 and refused to work with its supporters in Parliament.In the 1935 general election, the CCF ran a candidate against Mitchell in Hamilton East (while the Liberals, again, ran no candidate). The split in the labour and anti-Tory vote resulted in the Conservative candidate defeating Mitchell despite the nationwide trend against the Conservatives.Mitchell did not run in the 1940 election, however, following the death of Welland's Liberal MP in late 1941, Mitchell was appointed to the Cabinet of William Lyon Mackenzie King as Minister of Labour, and was elected shortly thereafter as the new Liberal MP for Welland. He served as Welland's MP and as Labour minister in the governments of King and Louis St. Laurent until his death in 1950.Miitchell became Labour minister just over a year after the introduction of unemployment insurance in Canada, and oversaw the early implementation and expansion of the program. He also oversaw the mobilization of the labour force during World War II, and the widespread introduction of women into war production.With the responsibilities his department had for immigration, he also had a controversial role in advocating and implementing the deportation or detention of tens of thousands of Japanese Canadians during the war.</pm:biography>
    </pm:biographies>
  </pm:member>
</root>
