<root xmlns:owl="http://www.w3.org/2002/07/owl#" xmlns:pmx="http://www.politicalmashup.nl/extra" xmlns:dc="http://purl.org/dc/elements/1.1/" xmlns:pmd="http://www.politicalmashup.nl/docinfo" xmlns:openpx="https://openparliament.ca/extra" xmlns:dcterms="http://purl.org/dc/terms/" xmlns:html="http://www.w3.org/1999/xhtml" xmlns:rdf="http://www.w3.org/1999/02/22-rdf-syntax-ns#" xmlns:xsd="http://www.w3.org/2001/XMLSchema-datatypes" xmlns:xsi="http://www.w3.org/2001/XMLSchema-instance" xmlns:pm="http://www.politicalmashup.nl">
  <pmd:docinfo>
    <pm:comment>Data is valid with respect to the Relax NG schema http://schema.politicalmashup.nl/memberX.html. This is the open version of http://schema.politicalmashup.nl/member.html</pm:comment>
  </pmd:docinfo>
  <meta pm:id="ca.m.1081">
    <dc:identifier/>
    <dc:format>text/xml</dc:format>
    <dc:type>Members</dc:type>
    <dc:contributor>http://www.politicalmashup.nl</dc:contributor>
    <dc:coverage>
      <country dcterms:ISO3166-1="CA">Canada</country>
    </dc:coverage>
    <dc:creator>http://dilipad.history.ac.uk</dc:creator>
    <dc:language>
      <pm:language dcterms:ISO639-2="eng">English</pm:language>
    </dc:language>
    <dc:publisher>http://www.parl.gc.ca/parlinfo/</dc:publisher>
    <dc:rights>http://www.parl.gc.ca/parlinfo/</dc:rights>
    <dc:date>2015-08-08+01:00</dc:date>
    <dc:title>KENDRY,  James</dc:title>
    <dc:description>Member information for: KENDRY,  James</dc:description>
    <dc:source>
      <dc:source pm:used-source="true">
        <pm:link pm:linktype="trusted" pm:source="http://www.parl.gc.ca/parlinfo">http://www.parl.gc.ca/parlinfo</pm:link>
      </dc:source>
      <dc:source pm:used-source="true">
        <pm:link pm:linktype="trusted" pm:source="http://www.parl.gc.ca/ParlInfo/Files/Parliamentarian.aspx?Item=ca7c4a6e-291b-4873-8c2d-10152eff92b8&amp;Language=E&amp;Section=ALL">http://www.parl.gc.ca/ParlInfo/Files/Parliamentarian.aspx?Item=ca7c4a6e-291b-4873-8c2d-10152eff92b8&amp;Language=E&amp;Section=ALL</pm:link>
      </dc:source>
    </dc:source>
    <dc:subject/>
    <dc:relation>All pm:party-ref attributes appearing in http://www.politicalmashup.nl documents refer to http://resolver.politicalmashup.nl/[pm:party-ref] .</dc:relation>
  </meta>
  <pm:member pm:id="ca.m.1081">
    <pm:name>
      <pm:full>KENDRY,  James</pm:full>
      <pm:first>James</pm:first>
      <pm:last>Kendry</pm:last>
    </pm:name>
    <pm:personal>
      <pm:born pm:date="1845-03-29" pm:granularity="8" pm:place="Oshawa, Canada West"/>
      <pm:deceased pm:date="1918-11-04" pm:granularity="8"/>
      <pm:gender>male</pm:gender>
    </pm:personal>
    <pm:curriculum>
      <pm:extra-curricular pm:source="http://www.parl.gc.ca/parlinfo/">
        <pm:name>Woollens manufacturer</pm:name>
      </pm:extra-curricular>
    </pm:curriculum>
    <pm:links>
      <pm:link pm:linktype="trusted" pm:source="http://www.parl.gc.ca/parlinfo" pm:description="Parlinfo">http://www.parl.gc.ca/ParlInfo/Files/Parliamentarian.aspx?Item=ca7c4a6e-291b-4873-8c2d-10152eff92b8&amp;Language=E&amp;Section=ALL</pm:link>
      <pm:link pm:linktype="photo" pm:source="http://www.parl.gc.ca/parlinfo" pm:description="Portrait photo Parlinfo">http://www.parl.gc.ca/parlinfo/images/Picture.aspx?Item=a42f3478-9f14-4a6c-ab50-752ee8d3cf6d</pm:link>
      <pm:link pm:linktype="dbpedia" pm:source="http://dbpedia.org" pm:description="Dbpedia ()">http://dbpedia.org/resource/James_Kendry</pm:link>
      <pm:link pm:linktype="wikipedia" pm:source="http://en.wikipedia.org" pm:description="Wikipedia (EN)">http://en.wikipedia.org/wiki/James_Kendry</pm:link>
    </pm:links>
    <pm:memberships>
      <pm:membership pm:body="commons" pm:district="Peterborough West" openpx:province="Ontario">
        <pm:period pm:from="1900-11-07" pm:from-granularity="8" pm:till="1904-09-29" pm:till-granularity="8"/>
      </pm:membership>
      <pm:membership pm:body="commons" pm:district="Peterborough West" openpx:province="Ontario">
        <pm:period pm:from="1896-06-23" pm:from-granularity="8" pm:till="1900-10-09" pm:till-granularity="8"/>
      </pm:membership>
    <pm:membership pm:party-name="Conservative (1867-1942)" pm:party-ref="ca.p.conservative1942" pm:body="other">
        <pm:period pm:from="1896-06-23" pm:from-granularity="8" pm:till="1904-11-02" pm:till-granularity="8"/>
      </pm:membership>
    </pm:memberships>
    <pm:biographies>
      <pm:biography pm:source="http://dbpedia.org/page/James_Kendry">James Kendry (March 29, 1845 – November 4, 1918) was a woollen manufacturer and political figure in Ontario, Canada. He represented Peterborough West in the Canadian House of Commons from 1896 to 1904 as a Conservative.He was born in Oshawa, Canada West and was educated there. Kendry was manager of the Clyde Woolen Mills in Lanark. In 1879, he became manager of the Auburn Woollen Mills in Peterborough and later became an owner. Kendry was mayor of Peterborough from 1892 to 1896. He was defeated when he ran for reelection to the House of Commons in 1904. He died in Peterborough at the age of 73.</pm:biography>
    </pm:biographies>
  </pm:member>
</root>
