<root xmlns:owl="http://www.w3.org/2002/07/owl#" xmlns:pmx="http://www.politicalmashup.nl/extra" xmlns:dc="http://purl.org/dc/elements/1.1/" xmlns:pmd="http://www.politicalmashup.nl/docinfo" xmlns:openpx="https://openparliament.ca/extra" xmlns:dcterms="http://purl.org/dc/terms/" xmlns:html="http://www.w3.org/1999/xhtml" xmlns:rdf="http://www.w3.org/1999/02/22-rdf-syntax-ns#" xmlns:xsd="http://www.w3.org/2001/XMLSchema-datatypes" xmlns:xsi="http://www.w3.org/2001/XMLSchema-instance" xmlns:pm="http://www.politicalmashup.nl">
  <pmd:docinfo>
    <pm:comment>Data is valid with respect to the Relax NG schema http://schema.politicalmashup.nl/memberX.html. This is the open version of http://schema.politicalmashup.nl/member.html</pm:comment>
  </pmd:docinfo>
  <meta pm:id="ca.m.7702">
    <dc:identifier/>
    <dc:format>text/xml</dc:format>
    <dc:type>Members</dc:type>
    <dc:contributor>http://www.politicalmashup.nl</dc:contributor>
    <dc:coverage>
      <country dcterms:ISO3166-1="CA">Canada</country>
    </dc:coverage>
    <dc:creator>http://dilipad.history.ac.uk</dc:creator>
    <dc:language>
      <pm:language dcterms:ISO639-2="eng">English</pm:language>
    </dc:language>
    <dc:publisher>http://www.parl.gc.ca/parlinfo/</dc:publisher>
    <dc:rights>http://www.parl.gc.ca/parlinfo/</dc:rights>
    <dc:date>2015-06-30+01:00</dc:date>
    <dc:title>CARROLL,  William F., B.A., LL.B.</dc:title>
    <dc:description>Member information for: CARROLL,  William F., B.A., LL.B.</dc:description>
    <dc:source>
      <dc:source pm:used-source="true">
        <pm:link pm:linktype="trusted" pm:source="http://www.parl.gc.ca/parlinfo">http://www.parl.gc.ca/parlinfo</pm:link>
      </dc:source>
      <dc:source pm:used-source="true">
        <pm:link pm:linktype="trusted" pm:source="http://www.parl.gc.ca/ParlInfo/Files/Parliamentarian.aspx?Item=78eadf97-c6a9-462a-b669-6f6616adf0ba&amp;Language=E&amp;Section=ALL">http://www.parl.gc.ca/ParlInfo/Files/Parliamentarian.aspx?Item=78eadf97-c6a9-462a-b669-6f6616adf0ba&amp;Language=E&amp;Section=ALL</pm:link>
      </dc:source>
    </dc:source>
    <dc:subject/>
    <dc:relation>All pm:party-ref attributes appearing in http://www.politicalmashup.nl documents refer to http://resolver.politicalmashup.nl/[pm:party-ref] .</dc:relation>
  </meta>
  <pm:member pm:id="ca.m.7702">
    <pm:name>
      <pm:full>CARROLL,  William F., B.A., LL.B.</pm:full>
      <pm:first>William F.</pm:first>
      <pm:last>Carroll</pm:last>
      <pm:titles>
        <pm:title pm:position="suffix" pm:honorific="academic">B.A.</pm:title>
        <pm:title pm:position="suffix" pm:honorific="academic">LL.B.</pm:title>
      </pm:titles>
    </pm:name>
    <pm:personal>
      <pm:born pm:date="1877-06-11" pm:granularity="8" pm:place="Margaree Forks, Nova Scotia, Canada"/>
      <pm:deceased pm:date="1964-08-25" pm:granularity="8"/>
      <pm:gender>male</pm:gender>
    </pm:personal>
    <pm:curriculum>
      <pm:extra-curricular pm:source="http://www.parl.gc.ca/parlinfo/">
        <pm:name>Barrister, judge, lawyer</pm:name>
      </pm:extra-curricular>
    </pm:curriculum>
    <pm:links>
      <pm:link pm:linktype="trusted" pm:source="http://www.parl.gc.ca/parlinfo" pm:description="Parlinfo">http://www.parl.gc.ca/ParlInfo/Files/Parliamentarian.aspx?Item=78eadf97-c6a9-462a-b669-6f6616adf0ba&amp;Language=E&amp;Section=ALL</pm:link>
      <pm:link pm:linktype="photo" pm:source="http://www.parl.gc.ca/parlinfo" pm:description="Portrait photo Parlinfo">http://www.parl.gc.ca/parlinfo/images/Picture.aspx?Item=85ebdd9a-3ff7-4b85-92b3-e367fa9c116d</pm:link>
      <pm:link pm:linktype="dbpedia" pm:source="http://dbpedia.org" pm:description="Dbpedia ()">http://dbpedia.org/resource/William_F._Carroll</pm:link>
      <pm:link pm:linktype="wikipedia" pm:source="http://en.wikipedia.org" pm:description="Wikipedia (EN)">http://en.wikipedia.org/wiki/William_F._Carroll</pm:link>
    </pm:links>
    <pm:memberships>
      <pm:membership pm:body="commons" pm:district="Inverness--Richmond" openpx:province="Nova Scotia">
        <pm:period pm:from="1949-06-27" pm:from-granularity="8" pm:till="1953-06-13" pm:till-granularity="8"/>
      </pm:membership>
      <pm:membership pm:body="commons" pm:district="Cape Breton South and Richmond" openpx:province="Nova Scotia">
        <pm:period pm:from="1921-12-06" pm:from-granularity="8" pm:till="1925-09-05" pm:till-granularity="8"/>
      </pm:membership>
      <pm:membership pm:body="commons" pm:district="Cape Breton South" openpx:province="Nova Scotia">
        <pm:period pm:from="1911-09-21" pm:from-granularity="8" pm:till="1917-10-06" pm:till-granularity="8"/>
      </pm:membership>
    <pm:membership pm:party-name="Liberal" pm:party-ref="ca.p.liberal" pm:body="other">
        <pm:period pm:from="1949-06-27" pm:from-granularity="8" pm:till="1953-08-09" pm:till-granularity="8"/>
      </pm:membership>
      <pm:membership pm:party-name="Liberal" pm:party-ref="ca.p.liberal" pm:body="other">
        <pm:period pm:from="1921-12-06" pm:from-granularity="8" pm:till="1925-10-28" pm:till-granularity="8"/>
      </pm:membership>
      <pm:membership pm:party-name="Liberal" pm:party-ref="ca.p.liberal" pm:body="other">
        <pm:period pm:from="1911-09-21" pm:from-granularity="8" pm:till="1917-12-16" pm:till-granularity="8"/>
      </pm:membership>
    </pm:memberships>
    <pm:biographies>
      <pm:biography pm:source="http://dbpedia.org/page/William_F._Carroll">William Francis Carroll (June 11, 1877 – August 25, 1964) was a lawyer, judge and political figure in Nova Scotia, Canada. He represented Cape Breton South from 1911 to 1917, Cape Breton South and Richmond from 1921 to 1925 and Inverness—Richmond from 1949 to 1953 in the Canadian House of Commons as a Liberal member.He was born in Margaree Forks, Nova Scotia, the son of John Carroll, the son of an Irish immigrant, and Ellen Tompkins. Carroll was educated at Saint Francis Xavier University and Dalhousie University, was called to the Nova Scotia bar in 1905 and set up practice in Glace Bay. In 1906, he married Helen Curry. Carroll served as a lieutenant in the Canadian Expeditionary Force during World War I. He was defeated when he ran for reelection in 1917. In 1925, he was named to the Supreme Court of Nova Scotia; he was also named a judge of Admiralty in 1937. Carroll resigned from the bench in 1949 to run again federally. He died in Halifax at the age of 87.His grandson John Murphy also served in the House of Commons.</pm:biography>
    </pm:biographies>
  </pm:member>
</root>
